{
  "\u6de1\u6de1\u5fae\u7b11\u65b0": "https://weibo.com/u/2037138683",
  "\u7c89\u8272QI": "https://weibo.com/u/5457120225",
  "\u68a6\u5e7b\u718f\u8863\u8349A": "https://weibo.com/u/5262016689",
  "\u9c9c\u679c\u94fa\u5b50\u96f6\u98df\u4e13\u5356": "https://weibo.com/u/5455464951",
  "\u7a7f\u9a6c\u7532\u8bf4\u98ce\u8bdd": "https://weibo.com/u/2075135025",
  "\u5c0f\u96e8\u548c\u949f\u7684\u4e56": "https://weibo.com/u/1773271317",
  "\u7528\u62375243888606": "https://weibo.com/u/5243888606",
  "\u9752\u9614\u8783\u871e": "https://weibo.com/u/2665847833",
  "101memory": "https://weibo.com/u/3464981742",
  "TraditionalCVisMoreDifficult": "https://weibo.com/u/1839160272",
  "YaYa\u590f\u4ed5\u51e4": "https://weibo.com/u/3030636824",
  "\u7528\u62375479876869": "https://weibo.com/u/5479876869",
  "\u6002\u5c15": "https://weibo.com/u/5419490114",
  "zzhwsw": "https://weibo.com/u/1783839574",
  "\u627f\u6c34\u4e00\u95fb": "https://weibo.com/u/5361833460",
  "\u5c0f\u660e\u5c0f\u7ea2\u548c\u5c0f\u9ec4": "https://weibo.com/u/2569087957",
  "\u6668\u560e": "https://weibo.com/u/5307007764",
  "\u7528\u62372793682580": "https://weibo.com/u/2793682580",
  "-\u848b\u848b_": "https://weibo.com/u/5307851079",
  "\u4f36\u4f36\u4f5c\u54cd": "https://weibo.com/u/5399875137",
  "\u4e09\u5170\u5ddd_401": "https://weibo.com/u/5271797187",
  "\u8001\u533a\u4e0d\u518d\u8001": "https://weibo.com/u/1663734401",
  "\u88ab\u9178\u5230\u4e86": "https://weibo.com/u/5114469208",
  "\u60ac\u58f6\u9189\u4eba\u95f4": "https://weibo.com/u/2628679431",
  "xiaowen596": "https://weibo.com/u/5479059625",
  "c\u7eaa\u79bb": "https://weibo.com/u/5479278566",
  "\u5c31\u662f\u60f3\u6539\u4e2a\u540d\u5b5788": "https://weibo.com/u/2445974201",
  "\u4e07\u5c71\u5fae\u5e97": "https://weibo.com/u/3983288059",
  "\u7528\u62375467012928": "https://weibo.com/u/5467012928",
  "\u786c\u58f3\u7b28\u86cb": "https://weibo.com/u/1645665632",
  "\u7528\u62371046640370": "https://weibo.com/u/1046640370",
  "\u52c7\u8005\u65e0\u654c007\u519b\u519b": "https://weibo.com/u/1942606390",
  "\u4e0d\u518d\u6267\u5ff51211": "https://weibo.com/u/5429696226",
  "\u8c6a\u9999\u5c45": "https://weibo.com/u/5478450049",
  "\u56fe\u60a6DAVIS": "https://weibo.com/u/1237158944",
  "\u4e4c\u6d77\u516c\u5b89": "https://weibo.com/u/2263624977"
}